sysarray/rtl/PE.sv
module PE (
    input logic clk,
    input logic rst,
    input logic clear,
    input logic valid_in,
    input logic [7:0] a_in,
    input logic [7:0] b_in,
    output logic [7:0] a_out,
    output logic [7:0] b_out,
    output logic valid_out,
    output logic [31:0] acc
);
logic [7:0] a_reg;
logic [7:0] b_reg;
logic valid_reg;
logic [31:0] acc_reg;
always_ff @(posedge clk) begin
    if (rst) begin
        a_reg <= 8'd0;
        b_reg <= 8'd0;
        acc_reg <= 32'd0;
        valid_reg <= 1'b0;
    end
    else begin
        a_reg <=a_in;
        b_reg <=b_in;
        valid_reg <= valid_in;
        if (clear) begin
            acc_reg <=32'd0;
        end
        else if (valid_in) begin
            acc_reg <= acc_reg + (a_in * b_in);
        end
    end
end
assign a_out = a_reg;
assign b_out = b_reg;
assign valid_out = valid_reg;
assign acc = acc_reg;
endmodule

sysarray/rtl/PE_chain.sv
module PE_chain (
    input logic clk,
    input logic rst,
    input logic clear,
    input logic valid_in,
    input logic [7:0] a_in,
    input logic [7:0] b_in,
    output logic [7:0] a_out,
    output logic [7:0] b_out,
    output logic valid_out,
    output logic [31:0] acc0,
    output logic [31:0] acc1
);
logic [7:0] a_wire;
logic [7:0] b_wire;
logic valid_wire;

PE pe0 (
    .clk(clk),
    .rst(rst),
    .clear(clear),
    .valid_in(valid_in),
    .a_in(a_in),
    .b_in(b_in),
    .a_out(a_wire),
    .b_out(b_wire),
    .valid_out(valid_wire),
    .acc(acc0)
);
PE pe1 (
    .clk(clk),
    .rst(rst),
    .clear(clear),
    .valid_in(valid_wire),
    .a_in(a_wire),
    .b_in(b_wire),
    .a_out(a_out),
    .b_out(b_out),
    .valid_out(valid_out),
    .acc(acc1)
);
endmodule

sysarray/tb/PE_chain_tb.sv
module PE_chain_tb;
    logic clk;
    logic rst;
    logic clear;
    logic valid_in;
    logic [7:0] a_in;
    logic [7:0] b_in;
    logic [7:0] a_out;
    logic [7:0] b_out;
    logic valid_out;
    logic [31:0] acc0;
    logic [31:0] acc1;

    PE_chain dut (
        .clk(clk),
        .rst(rst),
        .clear(clear),
        .valid_in(valid_in),
        .a_in(a_in),
        .b_in(b_in),
        .a_out(a_out),
        .b_out(b_out),
        .valid_out(valid_out),
        .acc0(acc0),
        .acc1(acc1)
    );
    initial begin
        $dumpfile("PE_chain_tb.vcd");
        $dumpvars(0, PE_tb);
    end
    initial begin
        clk = 1'b0;
        forever begin
            #5 clk = ~clk;
        end 
    end
    initial begin
        rst = 1'b1;
        clear = 1'b0;
        valid_in = 1'b0;
        a_in = 8'd0;
        b_in = 8'd0;
        repeat (2) @(posedge clk);
        rst = 1'b0;
        @(negedge clk);
        a_in = 8'd3;
        b_in = 8'd2;
        valid_in = 1'b1;
        @(negedge clk);
        a_in = 8'd4;
        b_in = 8'd5;
        valid_in = 1'b1;
        @(negedge clk);
        a_in = 8'd7;
        b_in = 8'd2;
        valid_in = 1'b1;
        @(negedge clk);
        valid_in = 1'b0;
        repeat (2) @(posedge clk);
        $finish;
    end
    initial begin
        forever begin
            @(posedge clk);
            $strobe("Time=%0t,A_IN=%0d,B_IN=%0d,VALID_IN=%0b,A_OUT=%0d,B_OUT=%0d,VALID_OUT=%0b,ACC0=%0d,ACC1=%0d",$time,a_in,b_in,valid_in,a_out,b_out,valid_out,acc0,acc1);
        end
    end
endmodule

sysarray/PE_chain_tb.vcd
$version Generated by VerilatedVcd $end
$timescale 1ps $end
 $scope module PE_chain_tb $end
  $var wire 1 / clk $end
  $var wire 1 " rst $end
  $var wire 1 # clear $end
  $var wire 1 $ valid_in $end
  $var wire 8 % a_in [7:0] $end
  $var wire 8 & b_in [7:0] $end
  $var wire 8 ' a_out [7:0] $end
  $var wire 8 ( b_out [7:0] $end
  $var wire 1 ) valid_out $end
  $var wire 32 * acc0 [31:0] $end
  $var wire 32 + acc1 [31:0] $end
  $scope module dut $end
   $var wire 1 / clk $end
   $var wire 1 " rst $end
   $var wire 1 # clear $end
   $var wire 1 $ valid_in $end
   $var wire 8 % a_in [7:0] $end
   $var wire 8 & b_in [7:0] $end
   $var wire 8 ' a_out [7:0] $end
   $var wire 8 ( b_out [7:0] $end
   $var wire 1 ) valid_out $end
   $var wire 32 * acc0 [31:0] $end
   $var wire 32 + acc1 [31:0] $end
   $var wire 8 , a_wire [7:0] $end
   $var wire 8 - b_wire [7:0] $end
   $var wire 1 . valid_wire $end
   $scope module pe0 $end
    $var wire 1 / clk $end
    $var wire 1 " rst $end
    $var wire 1 # clear $end
    $var wire 1 $ valid_in $end
    $var wire 8 % a_in [7:0] $end
    $var wire 8 & b_in [7:0] $end
    $var wire 8 , a_out [7:0] $end
    $var wire 8 - b_out [7:0] $end
    $var wire 1 . valid_out $end
    $var wire 32 * acc [31:0] $end
    $var wire 8 , a_reg [7:0] $end
    $var wire 8 - b_reg [7:0] $end
    $var wire 1 . valid_reg $end
    $var wire 32 * acc_reg [31:0] $end
   $upscope $end
   $scope module pe1 $end
    $var wire 1 / clk $end
    $var wire 1 " rst $end
    $var wire 1 # clear $end
    $var wire 1 . valid_in $end
    $var wire 8 , a_in [7:0] $end
    $var wire 8 - b_in [7:0] $end
    $var wire 8 ' a_out [7:0] $end
    $var wire 8 ( b_out [7:0] $end
    $var wire 1 ) valid_out $end
    $var wire 32 + acc [31:0] $end
    $var wire 8 ' a_reg [7:0] $end
    $var wire 8 ( b_reg [7:0] $end
    $var wire 1 ) valid_reg $end
    $var wire 32 + acc_reg [31:0] $end
   $upscope $end
  $upscope $end
 $upscope $end
$enddefinitions $end


#0
1"
0#
0$
b00000000 %
b00000000 &
b00000000 '
b00000000 (
0)
b00000000000000000000000000000000 *
b00000000000000000000000000000000 +
b00000000 ,
b00000000 -
0.
0/
#5
1/
#10
0/
#15
0"
1/
#20
1$
b00000011 %
b00000010 &
0/
#25
b00000000000000000000000000000110 *
b00000011 ,
b00000010 -
1.
1/
#30
b00000100 %
b00000101 &
0/
#35
b00000011 '
b00000010 (
1)
b00000000000000000000000000011010 *
b00000000000000000000000000000110 +
b00000100 ,
b00000101 -
1/
#40
b00000111 %
b00000010 &
0/
#45
b00000100 '
b00000101 (
b00000000000000000000000000101000 *
b00000000000000000000000000011010 +
b00000111 ,
b00000010 -
1/
#50
0$
0/
#55
b00000111 '
b00000010 (
b00000000000000000000000000101000 +
0.
1/
#60
0/
#65
0)
1/
