sysarray/rtl/PE_systolic.sv
`timescale 1ns/1ps

module PE_systolic(
     input logic clk,
     input logic rst,
     input logic clear,
     input logic [7:0] a_in,
     input logic [7:0] b_in,
     input logic a_valid_in,
     input logic b_valid_in, 
     output logic [7:0] a_out,
     output logic [7:0] b_out,
     output logic a_valid_out,
     output logic b_valid_out,
     output logic [31:0] acc
);
logic [7:0] a_reg;
logic [7:0] b_reg;
logic a_valid_reg;
logic b_valid_reg;
logic [31:0] acc_reg;

always_ff @(posedge clk)
begin
    if (rst)begin
        a_reg <= 8'd0;
        b_reg <= 8'd0;
        a_valid_reg <= 1'b0;
        b_valid_reg <= 1'b0;
        acc_reg <= 32'd0;
    end
    else begin
        a_reg <= a_in;
        a_valid_reg <= a_valid_in;
        b_reg <= b_in;
        b_valid_reg <= b_valid_in;
        if (clear) begin
            acc_reg <= 32'd0;
        end

        else if (a_valid_in && b_valid_in) begin
            acc_reg <= acc_reg + (a_in*b_in);
        end
    end
end
assign a_out = a_reg;
assign a_valid_out = a_valid_reg;
assign b_out = b_reg;
assign b_valid_out = b_valid_reg;
assign acc = acc_reg;
endmodule

sysarray/rtl/PE_sysarray.sv
`timescale 1ns/1ps

module PE_sysarray #(parameter int N=2)(
    input logic clk,
    input logic rst,
    input logic clear,
    input logic [7:0] a_in[N],
    input logic [7:0] b_in[N],
    input logic a_valid_in[N],
    input logic b_valid_in[N], 
    output logic [31:0] acc[N][N]
);  
logic [7:0] a_wire [N][N];
logic [7:0] b_wire [N][N];
logic valid_a_wire [N][N];
logic valid_b_wire [N][N];
genvar i,j;
generate 
    for (i=0;i<N;i++) begin :row
        for (j=0;j<N;j++) begin :col
            PE_systolic pe(
                .clk(clk),
                .rst(rst),
                .clear(clear),
                .a_in(j==0 ? a_in[i]:a_wire[i][j-1]),
                .b_in(i==0 ? b_in[j]:b_wire[i-1][j]),
                .a_valid_in(j==0 ? a_valid_in[i]:valid_a_wire[i][j-1]),
                .b_valid_in(i==0 ? b_valid_in[j]:valid_b_wire[i-1][j]),
                .a_out(a_wire[i][j]),
                .b_out(b_wire[i][j]),
                .a_valid_out(valid_a_wire[i][j]),
                .b_valid_out(valid_b_wire[i][j]),
                .acc(acc[i][j])
            );
        end
    end
endgenerate
endmodule

sysarray/tb/PE_sysarray_tb.sv
`timescale 1ns/1ps

module PE_sysarray_tb;
    parameter int N = 2;
    logic clk;
    logic rst;
    logic clear;
    logic [7:0] a_in [N];
    logic [7:0] b_in [N];
    logic a_valid_in [N];
    logic b_valid_in [N];
    logic [31:0] acc [N][N];
    PE_sysarray #(
        .N(N)
    ) dut (
        .clk(clk),
        .rst(rst),
        .clear(clear),
        .a_in(a_in),
        .b_in(b_in),
        .a_valid_in(a_valid_in),
        .b_valid_in(b_valid_in),
        .acc(acc)
    );
    always #5 clk = ~clk;
    initial begin
        $dumpfile("PE_sysarray.vcd");
        $dumpvars(0, PE_sysarray_tb);
        clk = 1'b0;
        rst = 1'b1;
        clear = 1'b1;
        for (int i = 0; i < N; i++) begin
            a_in[i] = 8'd0;
            b_in[i] = 8'd0;
            a_valid_in[i] = 1'b0;
            b_valid_in[i] = 1'b0;
        end
        #20;
        rst = 1'b0;
        clear = 1'b0;
        @(negedge clk);
        a_in[0] = 8'd1;
        a_in[1] = 8'd0;
        b_in[0] = 8'd5;
        b_in[1] = 8'd0;
        a_valid_in[0] = 1'b1;
        a_valid_in[1] = 1'b0;
        b_valid_in[0] = 1'b1;
        b_valid_in[1] = 1'b0;
        @(negedge clk);
        a_in[0] = 8'd2;
        a_in[1] = 8'd3;
        b_in[0] = 8'd7;
        b_in[1] = 8'd6;
        a_valid_in[0] = 1'b1;
        a_valid_in[1] = 1'b1;
        b_valid_in[0] = 1'b1;
        b_valid_in[1] = 1'b1;
        @(negedge clk);
        a_in[0] = 8'd0;
        a_in[1] = 8'd4;
        b_in[0] = 8'd0;
        b_in[1] = 8'd8;
        a_valid_in[0] = 1'b0;
        a_valid_in[1] = 1'b1;
        b_valid_in[0] = 1'b0;
        b_valid_in[1] = 1'b1;
        @(negedge clk);
        for (int i = 0; i < N; i++) begin
            a_in[i] = 8'd0;
            b_in[i] = 8'd0;
            a_valid_in[i] = 1'b0;
            b_valid_in[i] = 1'b0;
        end
        repeat (5)
            @(posedge clk);
        $display("ACC00 = %0d", acc[0][0]);
        $display("ACC01 = %0d", acc[0][1]);
        $display("ACC10 = %0d", acc[1][0]);
        $display("ACC11 = %0d", acc[1][1]);
        $finish;
    end
endmodule

sysarray/PE_sysarray.vcd
$version Generated by VerilatedVcd $end
$timescale 1ps $end
 $scope module PE_sysarray_tb $end
  $var wire 32 e N [31:0] $end
  $var wire 1 d clk $end
  $var wire 1 " rst $end
  $var wire 1 # clear $end
  $var wire 8 $ a_in[0] [7:0] $end
  $var wire 8 % a_in[1] [7:0] $end
  $var wire 8 & b_in[0] [7:0] $end
  $var wire 8 ' b_in[1] [7:0] $end
  $var wire 1 ( a_valid_in[0] $end
  $var wire 1 ) a_valid_in[1] $end
  $var wire 1 * b_valid_in[0] $end
  $var wire 1 + b_valid_in[1] $end
  $var wire 32 4 acc[0][0] [31:0] $end
  $var wire 32 5 acc[0][1] [31:0] $end
  $var wire 32 6 acc[1][0] [31:0] $end
  $var wire 32 7 acc[1][1] [31:0] $end
  $scope module dut $end
   $var wire 32 e N [31:0] $end
   $var wire 1 d clk $end
   $var wire 1 " rst $end
   $var wire 1 # clear $end
   $var wire 8 $ a_in[0] [7:0] $end
   $var wire 8 % a_in[1] [7:0] $end
   $var wire 8 & b_in[0] [7:0] $end
   $var wire 8 ' b_in[1] [7:0] $end
   $var wire 1 ( a_valid_in[0] $end
   $var wire 1 ) a_valid_in[1] $end
   $var wire 1 * b_valid_in[0] $end
   $var wire 1 + b_valid_in[1] $end
   $var wire 32 4 acc[0][0] [31:0] $end
   $var wire 32 5 acc[0][1] [31:0] $end
   $var wire 32 6 acc[1][0] [31:0] $end
   $var wire 32 7 acc[1][1] [31:0] $end
   $var wire 8 8 a_wire[0][0] [7:0] $end
   $var wire 8 9 a_wire[0][1] [7:0] $end
   $var wire 8 : a_wire[1][0] [7:0] $end
   $var wire 8 ; a_wire[1][1] [7:0] $end
   $var wire 8 < b_wire[0][0] [7:0] $end
   $var wire 8 = b_wire[0][1] [7:0] $end
   $var wire 8 > b_wire[1][0] [7:0] $end
   $var wire 8 ? b_wire[1][1] [7:0] $end
   $var wire 1 @ valid_a_wire[0][0] $end
   $var wire 1 A valid_a_wire[0][1] $end
   $var wire 1 B valid_a_wire[1][0] $end
   $var wire 1 C valid_a_wire[1][1] $end
   $var wire 1 D valid_b_wire[0][0] $end
   $var wire 1 E valid_b_wire[0][1] $end
   $var wire 1 F valid_b_wire[1][0] $end
   $var wire 1 G valid_b_wire[1][1] $end
   $scope module row[0] $end
    $scope module col[0] $end
     $scope module pe $end
      $var wire 1 d clk $end
      $var wire 1 " rst $end
      $var wire 1 # clear $end
      $var wire 8 , a_in [7:0] $end
      $var wire 8 - b_in [7:0] $end
      $var wire 1 . a_valid_in $end
      $var wire 1 / b_valid_in $end
      $var wire 8 H a_out [7:0] $end
      $var wire 8 I b_out [7:0] $end
      $var wire 1 J a_valid_out $end
      $var wire 1 K b_valid_out $end
      $var wire 32 L acc [31:0] $end
      $var wire 8 H a_reg [7:0] $end
      $var wire 8 I b_reg [7:0] $end
      $var wire 1 J a_valid_reg $end
      $var wire 1 K b_valid_reg $end
      $var wire 32 L acc_reg [31:0] $end
     $upscope $end
    $upscope $end
    $scope module col[1] $end
     $scope module pe $end
      $var wire 1 d clk $end
      $var wire 1 " rst $end
      $var wire 1 # clear $end
      $var wire 8 M a_in [7:0] $end
      $var wire 8 0 b_in [7:0] $end
      $var wire 1 N a_valid_in $end
      $var wire 1 1 b_valid_in $end
      $var wire 8 O a_out [7:0] $end
      $var wire 8 P b_out [7:0] $end
      $var wire 1 Q a_valid_out $end
      $var wire 1 R b_valid_out $end
      $var wire 32 S acc [31:0] $end
      $var wire 8 O a_reg [7:0] $end
      $var wire 8 P b_reg [7:0] $end
      $var wire 1 Q a_valid_reg $end
      $var wire 1 R b_valid_reg $end
      $var wire 32 S acc_reg [31:0] $end
     $upscope $end
    $upscope $end
   $upscope $end
   $scope module row[1] $end
    $scope module col[0] $end
     $scope module pe $end
      $var wire 1 d clk $end
      $var wire 1 " rst $end
      $var wire 1 # clear $end
      $var wire 8 2 a_in [7:0] $end
      $var wire 8 T b_in [7:0] $end
      $var wire 1 3 a_valid_in $end
      $var wire 1 U b_valid_in $end
      $var wire 8 V a_out [7:0] $end
      $var wire 8 W b_out [7:0] $end
      $var wire 1 X a_valid_out $end
      $var wire 1 Y b_valid_out $end
      $var wire 32 Z acc [31:0] $end
      $var wire 8 V a_reg [7:0] $end
      $var wire 8 W b_reg [7:0] $end
      $var wire 1 X a_valid_reg $end
      $var wire 1 Y b_valid_reg $end
      $var wire 32 Z acc_reg [31:0] $end
     $upscope $end
    $upscope $end
    $scope module col[1] $end
     $scope module pe $end
      $var wire 1 d clk $end
      $var wire 1 " rst $end
      $var wire 1 # clear $end
      $var wire 8 [ a_in [7:0] $end
      $var wire 8 \ b_in [7:0] $end
      $var wire 1 ] a_valid_in $end
      $var wire 1 ^ b_valid_in $end
      $var wire 8 _ a_out [7:0] $end
      $var wire 8 ` b_out [7:0] $end
      $var wire 1 a a_valid_out $end
      $var wire 1 b b_valid_out $end
      $var wire 32 c acc [31:0] $end
      $var wire 8 _ a_reg [7:0] $end
      $var wire 8 ` b_reg [7:0] $end
      $var wire 1 a a_valid_reg $end
      $var wire 1 b b_valid_reg $end
      $var wire 32 c acc_reg [31:0] $end
     $upscope $end
    $upscope $end
   $upscope $end
  $upscope $end
 $upscope $end
$enddefinitions $end


#0
1"
1#
b00000000 $
b00000000 %
b00000000 &
b00000000 '
0(
0)
0*
0+
b00000000 ,
b00000000 -
0.
0/
b00000000 0
01
b00000000 2
03
b00000000000000000000000000000000 4
b00000000000000000000000000000000 5
b00000000000000000000000000000000 6
b00000000000000000000000000000000 7
b00000000 8
b00000000 9
b00000000 :
b00000000 ;
b00000000 <
b00000000 =
b00000000 >
b00000000 ?
0@
0A
0B
0C
0D
0E
0F
0G
b00000000 H
b00000000 I
0J
0K
b00000000000000000000000000000000 L
b00000000 M
0N
b00000000 O
b00000000 P
0Q
0R
b00000000000000000000000000000000 S
b00000000 T
0U
b00000000 V
b00000000 W
0X
0Y
b00000000000000000000000000000000 Z
b00000000 [
b00000000 \
0]
0^
b00000000 _
b00000000 `
0a
0b
b00000000000000000000000000000000 c
0d
b00000000000000000000000000000010 e
#5000
1d
#10000
0d
#15000
1d
#20000
0"
0#
b00000001 $
b00000101 &
1(
1*
b00000001 ,
b00000101 -
1.
1/
0d
#25000
b00000000000000000000000000000101 4
b00000001 8
b00000101 <
1@
1D
b00000001 H
b00000101 I
1J
1K
b00000000000000000000000000000101 L
b00000001 M
1N
b00000101 T
1U
1d
#30000
b00000010 $
b00000011 %
b00000111 &
b00000110 '
1)
1+
b00000010 ,
b00000111 -
b00000110 0
11
b00000011 2
13
0d
#35000
b00000000000000000000000000010011 4
b00000000000000000000000000000110 5
b00000000000000000000000000001111 6
b00000010 8
b00000001 9
b00000011 :
b00000111 <
b00000110 =
b00000101 >
1A
1B
1E
1F
b00000010 H
b00000111 I
b00000000000000000000000000010011 L
b00000010 M
b00000001 O
b00000110 P
1Q
1R
b00000000000000000000000000000110 S
b00000111 T
b00000011 V
b00000101 W
1X
1Y
b00000000000000000000000000001111 Z
b00000011 [
b00000110 \
1]
1^
1d
#40000
b00000000 $
b00000100 %
b00000000 &
b00001000 '
0(
0*
b00000000 ,
b00000000 -
0.
0/
b00001000 0
b00000100 2
0d
#45000
b00000000000000000000000000010110 5
b00000000000000000000000000101011 6
b00000000000000000000000000010010 7
b00000000 8
b00000010 9
b00000100 :
b00000011 ;
b00000000 <
b00001000 =
b00000111 >
b00000110 ?
0@
1C
0D
1G
b00000000 H
b00000000 I
0J
0K
b00000000 M
0N
b00000010 O
b00001000 P
b00000000000000000000000000010110 S
b00000000 T
0U
b00000100 V
b00000111 W
b00000000000000000000000000101011 Z
b00000100 [
b00001000 \
b00000011 _
b00000110 `
1a
1b
b00000000000000000000000000010010 c
1d
#50000
b00000000 %
b00000000 '
0)
0+
b00000000 0
01
b00000000 2
03
0d
#55000
b00000000000000000000000000110010 7
b00000000 9
b00000000 :
b00000100 ;
b00000000 =
b00000000 >
b00001000 ?
0A
0B
0E
0F
b00000000 O
b00000000 P
0Q
0R
b00000000 V
b00000000 W
0X
0Y
b00000000 [
b00000000 \
0]
0^
b00000100 _
b00001000 `
b00000000000000000000000000110010 c
1d
#60000
0d
#65000
b00000000 ;
b00000000 ?
0C
0G
b00000000 _
b00000000 `
0a
0b
1d
