sysarray/rtl/PE_systolic.sv
module PE_systolic(
     input logic clk,
     input logic rst,
     input logic clear,
     input logic [7:0] a_in,
     input logic [7:0] b_in,
     input logic a_valid_in,
     input logic b_valid_in, 
     output logic [7:0] a_out,
     output logic [7:0] b_out,
     output logic a_valid_out,
     output logic b_valid_out,
     output logic [31:0] acc
);
logic [7:0] a_reg;
logic [7:0] b_reg;
logic a_valid_reg;
logic b_valid_reg;
logic [31:0] acc_reg;

always_ff @(posedge clk)
begin
    if (rst)begin
        a_reg <= 8'd0;
        b_reg <= 8'd0;
        a_valid_reg <= 1'b0;
        b_valid_reg <= 1'b0;
        acc_reg <= 32'd0;
    end
    else begin
        a_reg <= a_in;
        a_valid_reg <= a_valid_in;
        b_reg <= b_in;
        b_valid_reg <= b_valid_in;
        if (clear) begin
            acc_reg <= 32'd0;
        end

        else if (a_valid_in && b_valid_in) begin
            acc_reg <= acc_reg + (a_in*b_in);
        end
    end
end
assign a_out       = a_reg;
assign a_valid_out = a_valid_reg;
assign b_out       = b_reg;
assign b_valid_out = b_valid_reg;
assign acc = acc_reg;
endmodule

sysarray/rtl/sys_2cross2.sv
module sys_2cross2(
    input logic clk,
    input logic rst,
    input logic clear,
    input logic [7:0] a0_in,
    input logic [7:0] a1_in,
    input logic [7:0] b0_in,
    input logic [7:0] b1_in,
    input logic valid_a0,
    input logic valid_a1,
    input logic valid_b0,
    input logic valid_b1,
    output logic [31:0] acc00,
    output logic [31:0] acc01,
    output logic [31:0] acc10,
    output logic [31:0] acc11
);
logic [7:0] a00_wire;
logic [7:0] b00_wire;
logic a_valid00_wire;
logic b_valid00_wire;
logic [7:0] a01_wire;
logic [7:0] b01_wire;
logic a_valid01_wire;
logic b_valid01_wire;
logic [7:0] a10_wire;
logic [7:0] b10_wire;
logic a_valid10_wire;
logic b_valid10_wire;
logic [7:0] a11_wire;
logic [7:0] b11_wire;
logic a_valid11_wire;
logic b_valid11_wire;

PE_systolic pe00(
    .clk(clk),
    .rst(rst),
    .clear(clear),
    .a_in(a0_in),
    .b_in(b0_in),
    .a_valid_in(valid_a0),
    .b_valid_in(valid_b0),
    .a_out(a00_wire),
    .b_out(b00_wire),
    .a_valid_out(a_valid00_wire),
    .b_valid_out(b_valid00_wire),
    .acc(acc00)
);

PE_systolic pe01(
    .clk(clk),
    .rst(rst),
    .clear(clear),
    .a_in(a00_wire),
    .b_in(b1_in),
    .a_valid_in(a_valid00_wire),
    .b_valid_in(valid_b1),
    .a_out(a01_wire),
    .b_out(b01_wire),
    .a_valid_out(a_valid01_wire),
    .b_valid_out(b_valid01_wire),
    .acc(acc01)
);

PE_systolic pe10(
    .clk(clk),
    .rst(rst),
    .clear(clear),
    .a_in(a1_in),
    .b_in(b00_wire),
    .a_valid_in(valid_a1),
    .b_valid_in(b_valid00_wire),
    .a_out(a10_wire),
    .b_out(b10_wire),
    .a_valid_out(a_valid10_wire),
    .b_valid_out(b_valid10_wire),
    .acc(acc10)
);

PE_systolic pe11(
    .clk(clk),
    .rst(rst),
    .clear(clear),
    .a_in(a10_wire),
    .b_in(b01_wire),
    .a_valid_in(a_valid10_wire),
    .b_valid_in(b_valid01_wire),
    .a_out(a11_wire),
    .b_out(b11_wire),
    .a_valid_out(a_valid11_wire),
    .b_valid_out(b_valid11_wire),
    .acc(acc11)
);
endmodule

sysarray/tb/sys_2cross2_tb.sv
module sys_2cross2_tb;

    logic clk;
    logic rst;
    logic clear;
    logic [7:0] a0_in;
    logic [7:0] a1_in;
    logic [7:0] b0_in;
    logic [7:0] b1_in;
    logic valid_a0;
    logic valid_a1;
    logic valid_b0;
    logic valid_b1;
    logic [31:0] acc00;
    logic [31:0] acc01;
    logic [31:0] acc10;
    logic [31:0] acc11;

    sys_2cross2 dut(
        .clk(clk),
        .rst(rst),
        .clear(clear),
        .a0_in(a0_in),
        .a1_in(a1_in),
        .b0_in(b0_in),
        .b1_in(b1_in),
        .valid_a0(valid_a0),
        .valid_a1(valid_a1),
        .valid_b0(valid_b0),
        .valid_b1(valid_b1),
        .acc00(acc00),
        .acc01(acc01),
        .acc10(acc10),
        .acc11(acc11)
    );
    initial begin
        $dumpfile("sys_2cross2.vcd");
        $dumpvars(0,sys_2cross2_tb);
    end
    initial begin
        clk = 1'b0;
        forever begin
            #5 clk = ~clk;
        end
    end
    initial begin
        rst = 1'b1;
        a0_in = 8'd0;
        a1_in = 8'd0;
        b0_in = 8'd0;
        b1_in = 8'd0;
        clear = 1'b0;
        valid_a0 = 1'b0;
        valid_a1 = 1'b0;
        valid_b0 = 1'b0;
        valid_b1 = 1'b0;
        repeat (2) @(posedge clk);
        rst = 1'b0;
        @(negedge clk)
        a0_in = 8'd1;
        valid_a0 = 1'b1;
        b0_in = 8'd5;
        valid_b0=1'b1;
        @(negedge clk)
        a0_in = 8'd2;
        valid_a0 = 1'b1;
        b0_in = 8'd7;
        valid_b0 = 1'b1;
        a1_in = 8'd3;
        valid_a1 = 1'b1;
        b1_in = 8'd6;
        valid_b1 = 1'b1;
        @(negedge clk)
        a0_in = 8'd0;
        valid_a0 = 1'b0;
        a1_in = 8'd4;
        valid_a1 = 1'b1;
        b0_in = 8'd0;
        valid_b0 = 1'b0;
        b1_in = 8'd8;
        valid_b1 = 1'b1;
        @(negedge clk);
        a0_in = 8'd0;
        a1_in = 8'd0;
        b0_in = 8'd0;
        b1_in = 8'd0;
        valid_a0 = 1'b0;
        valid_a1 = 1'b0;
        valid_b0 = 1'b0;
        valid_b1 = 1'b0;
        repeat (2) @(posedge clk);
        $finish;
    end
initial begin
    forever begin
        @(posedge clk);
        $strobe("TIME=%0t | A0=%0d V=%0b | A1=%0d V=%0b | B0=%0d V=%0b | B1=%0d V=%0b | ACC00=%0d | ACC01=%0d | ACC10=%0d | ACC11=%0d",$time,a0_in, valid_a0,a1_in, valid_a1,b0_in, valid_b0,b1_in, valid_b1,acc00,acc01,acc10,acc11);
    end
end

endmodule;

sysarray/sys_2cross2.vcd
$version Generated by VerilatedVcd $end
$timescale 1ps $end
 $scope module sys_2cross2_tb $end
  $var wire 1 @ clk $end
  $var wire 1 " rst $end
  $var wire 1 # clear $end
  $var wire 8 $ a0_in [7:0] $end
  $var wire 8 % a1_in [7:0] $end
  $var wire 8 & b0_in [7:0] $end
  $var wire 8 ' b1_in [7:0] $end
  $var wire 1 ( valid_a0 $end
  $var wire 1 ) valid_a1 $end
  $var wire 1 * valid_b0 $end
  $var wire 1 + valid_b1 $end
  $var wire 32 , acc00 [31:0] $end
  $var wire 32 - acc01 [31:0] $end
  $var wire 32 . acc10 [31:0] $end
  $var wire 32 / acc11 [31:0] $end
  $scope module dut $end
   $var wire 1 @ clk $end
   $var wire 1 " rst $end
   $var wire 1 # clear $end
   $var wire 8 $ a0_in [7:0] $end
   $var wire 8 % a1_in [7:0] $end
   $var wire 8 & b0_in [7:0] $end
   $var wire 8 ' b1_in [7:0] $end
   $var wire 1 ( valid_a0 $end
   $var wire 1 ) valid_a1 $end
   $var wire 1 * valid_b0 $end
   $var wire 1 + valid_b1 $end
   $var wire 32 , acc00 [31:0] $end
   $var wire 32 - acc01 [31:0] $end
   $var wire 32 . acc10 [31:0] $end
   $var wire 32 / acc11 [31:0] $end
   $var wire 8 0 a00_wire [7:0] $end
   $var wire 8 1 b00_wire [7:0] $end
   $var wire 1 2 a_valid00_wire $end
   $var wire 1 3 b_valid00_wire $end
   $var wire 8 4 a01_wire [7:0] $end
   $var wire 8 5 b01_wire [7:0] $end
   $var wire 1 6 a_valid01_wire $end
   $var wire 1 7 b_valid01_wire $end
   $var wire 8 8 a10_wire [7:0] $end
   $var wire 8 9 b10_wire [7:0] $end
   $var wire 1 : a_valid10_wire $end
   $var wire 1 ; b_valid10_wire $end
   $var wire 8 < a11_wire [7:0] $end
   $var wire 8 = b11_wire [7:0] $end
   $var wire 1 > a_valid11_wire $end
   $var wire 1 ? b_valid11_wire $end
   $scope module pe00 $end
    $var wire 1 @ clk $end
    $var wire 1 " rst $end
    $var wire 1 # clear $end
    $var wire 8 $ a_in [7:0] $end
    $var wire 8 & b_in [7:0] $end
    $var wire 1 ( a_valid_in $end
    $var wire 1 * b_valid_in $end
    $var wire 8 0 a_out [7:0] $end
    $var wire 8 1 b_out [7:0] $end
    $var wire 1 2 a_valid_out $end
    $var wire 1 3 b_valid_out $end
    $var wire 32 , acc [31:0] $end
    $var wire 8 0 a_reg [7:0] $end
    $var wire 8 1 b_reg [7:0] $end
    $var wire 1 2 a_valid_reg $end
    $var wire 1 3 b_valid_reg $end
    $var wire 32 , acc_reg [31:0] $end
   $upscope $end
   $scope module pe01 $end
    $var wire 1 @ clk $end
    $var wire 1 " rst $end
    $var wire 1 # clear $end
    $var wire 8 0 a_in [7:0] $end
    $var wire 8 ' b_in [7:0] $end
    $var wire 1 2 a_valid_in $end
    $var wire 1 + b_valid_in $end
    $var wire 8 4 a_out [7:0] $end
    $var wire 8 5 b_out [7:0] $end
    $var wire 1 6 a_valid_out $end
    $var wire 1 7 b_valid_out $end
    $var wire 32 - acc [31:0] $end
    $var wire 8 4 a_reg [7:0] $end
    $var wire 8 5 b_reg [7:0] $end
    $var wire 1 6 a_valid_reg $end
    $var wire 1 7 b_valid_reg $end
    $var wire 32 - acc_reg [31:0] $end
   $upscope $end
   $scope module pe10 $end
    $var wire 1 @ clk $end
    $var wire 1 " rst $end
    $var wire 1 # clear $end
    $var wire 8 % a_in [7:0] $end
    $var wire 8 1 b_in [7:0] $end
    $var wire 1 ) a_valid_in $end
    $var wire 1 3 b_valid_in $end
    $var wire 8 8 a_out [7:0] $end
    $var wire 8 9 b_out [7:0] $end
    $var wire 1 : a_valid_out $end
    $var wire 1 ; b_valid_out $end
    $var wire 32 . acc [31:0] $end
    $var wire 8 8 a_reg [7:0] $end
    $var wire 8 9 b_reg [7:0] $end
    $var wire 1 : a_valid_reg $end
    $var wire 1 ; b_valid_reg $end
    $var wire 32 . acc_reg [31:0] $end
   $upscope $end
   $scope module pe11 $end
    $var wire 1 @ clk $end
    $var wire 1 " rst $end
    $var wire 1 # clear $end
    $var wire 8 8 a_in [7:0] $end
    $var wire 8 5 b_in [7:0] $end
    $var wire 1 : a_valid_in $end
    $var wire 1 7 b_valid_in $end
    $var wire 8 < a_out [7:0] $end
    $var wire 8 = b_out [7:0] $end
    $var wire 1 > a_valid_out $end
    $var wire 1 ? b_valid_out $end
    $var wire 32 / acc [31:0] $end
    $var wire 8 < a_reg [7:0] $end
    $var wire 8 = b_reg [7:0] $end
    $var wire 1 > a_valid_reg $end
    $var wire 1 ? b_valid_reg $end
    $var wire 32 / acc_reg [31:0] $end
   $upscope $end
  $upscope $end
 $upscope $end
$enddefinitions $end


#0
1"
0#
b00000000 $
b00000000 %
b00000000 &
b00000000 '
0(
0)
0*
0+
b00000000000000000000000000000000 ,
b00000000000000000000000000000000 -
b00000000000000000000000000000000 .
b00000000000000000000000000000000 /
b00000000 0
b00000000 1
02
03
b00000000 4
b00000000 5
06
07
b00000000 8
b00000000 9
0:
0;
b00000000 <
b00000000 =
0>
0?
0@
#5
1@
#10
0@
#15
0"
1@
#20
b00000001 $
b00000101 &
1(
1*
0@
#25
b00000000000000000000000000000101 ,
b00000001 0
b00000101 1
12
13
1@
#30
b00000010 $
b00000011 %
b00000111 &
b00000110 '
1)
1+
0@
#35
b00000000000000000000000000010011 ,
b00000000000000000000000000000110 -
b00000000000000000000000000001111 .
b00000010 0
b00000111 1
b00000001 4
b00000110 5
16
17
b00000011 8
b00000101 9
1:
1;
1@
#40
b00000000 $
b00000100 %
b00000000 &
b00001000 '
0(
0*
0@
#45
b00000000000000000000000000010110 -
b00000000000000000000000000101011 .
b00000000000000000000000000010010 /
b00000000 0
b00000000 1
02
03
b00000010 4
b00001000 5
b00000100 8
b00000111 9
b00000011 <
b00000110 =
1>
1?
1@
#50
b00000000 %
b00000000 '
0)
0+
0@
#55
b00000000000000000000000000110010 /
b00000000 4
b00000000 5
06
07
b00000000 8
b00000000 9
0:
0;
b00000100 <
b00001000 =
1@
#60
0@
#65
b00000000 <
b00000000 =
0>
0?
1@
